ranking_sorting/__init__.py
ranking_sorting/hackernews_hot.py
ranking_sorting/wilson_score.py
ranking_sorting-0.0.9.dist-info/DESCRIPTION.rst
ranking_sorting-0.0.9.dist-info/METADATA
ranking_sorting-0.0.9.dist-info/RECORD
ranking_sorting-0.0.9.dist-info/WHEEL
ranking_sorting-0.0.9.dist-info/metadata.json
ranking_sorting-0.0.9.dist-info/top_level.txt
tests/__init__.py
tests/test_dummy.py
tests/test_hackernews_hot.py
tests/test_wilson_score.py
