Metadata-Version: 2.0
Name: ranking-sorting
Version: 0.0.9
Summary: Ranking and Sorting algorithms for vtalks.net
Home-page: https://github.com/vtalks/ranking_sorting
Author: Raül Pérez
Author-email: hellol@vtalks.net
License: Apache 2
Platform: UNKNOWN
Classifier: Programming Language :: Python :: 3
Classifier: License :: OSI Approved :: MIT License
Classifier: Operating System :: OS Independent
